{"users":[{"id":"3hrr6s1591","content":{"name":"Иван","mail":"mr-zerx@yandex.ru","date":"20.11.2023, 07:20","editDate":"изменений не было"}},{"id":"lrpn4l5773","content":{"name":"Пётр","mail":"mr-zerx@yandex.ru","date":"20.11.2023, 07:23","editDate":"изменений не было"}},{"id":"69yxum0325","content":{"name":"Пётр","mail":"voopoomode@gmail.com","date":"20.11.2023, 07:24","editDate":"изменений не было"}},{"id":"1ek8sy7904","content":{"name":"ghdfgs","mail":"voopoomode@gmail.com","date":"20.11.2023, 07:34","editDate":"изменений не было"}},{"id":"ob08ip1108","content":{"name":"Пётр","mail":"mr-zerx@yandex.ru","date":"20.11.2023, 07:35","editDate":"изменений не было"}},{"id":"6az6v70109","content":{"name":"Пётр","mail":"voopoomode@gmail.com","date":"21.11.2023, 00:25","editDate":"изменений не было"}},{"id":"lcv03i1050","content":{"name":"Констанстин","mail":"mr-zerx@yandex.ru","date":"21.11.2023, 03:11","editDate":"изменений не было"}},{"id":"3gu17w6247","content":{"name":"Иван","mail":"mr-zerx@yandex.ru","date":"21.11.2023, 03:11","editDate":"изменений не было"}},{"id":"a9x8l80979","content":{"name":"Пётр","mail":"voopoomode@gmail.com","date":"21.11.2023, 03:13","editDate":"изменений не было"}},{"id":"bpmiee6166","content":{"name":"Иван","mail":"mr-zerx@yandex.ru","date":"21.11.2023, 03:14","editDate":"изменений не было"}},{"id":"ocdy024635","content":{"name":"Пётр","mail":"voopoomode@gmail.com","date":"21.11.2023, 03:15","editDate":"изменений не было"}},{"id":"4n4bqz2445","content":{"name":"Сергей","mail":"mr-zerx@yandex.ru","date":"21.11.2023, 03:15","editDate":"изменений не было"}},{"id":"5b3f8r0144","content":{"name":"Констанстин","mail":"voopoomode@gmail.com","date":"21.11.2023, 03:17","editDate":"изменений не было"}},{"id":"pmpkbz5957","content":{"name":"Иван","mail":"mr-zerx@yandex.ru","date":"21.11.2023, 03:21","editDate":"изменений не было"}},{"id":"ui92ik0257","content":{"name":"sdfg","mail":"voopoomode@gmail.com","date":"21.11.2023, 04:14","editDate":"изменений не было"}},{"id":"tc37by7013","content":{"name":"Констанстин","mail":"mr-zerx@yandex.ru","date":"21.11.2023, 04:15","editDate":"изменений не было"}},{"id":"03gejm2160","content":{"name":"Пётр","mail":"mr-zerx@yandex.ru","date":"21.11.2023, 04:20","editDate":"изменений не было"}},{"id":"f0ienv9635","content":{"name":"Пётр3","mail":"voopoomode@gmail.combvcn","date":"21.11.2023, 04:20","editDate":"изменений не было"}},{"id":"sb625z5637","content":{"name":"Сергей","mail":"mr-zerx@yandex.ru","date":"21.11.2023, 04:21","editDate":"изменений не было"}},{"id":"digjg04203","content":{"name":"Сергей","mail":"sdf","date":"21.11.2023, 04:23","editDate":"изменений не было"}},{"id":"pvak0m4620","content":{"name":"Пётр","mail":"mr-zerx@yandex.ru","date":"21.11.2023, 04:37","editDate":"изменений не было"}},{"id":"4nvejg7585","content":{"name":"Пётр","mail":"mr-zerx@yandex.ru","date":"21.11.2023, 04:49","editDate":"изменений не было"}},{"id":"u4aes88587","content":{"name":"Иван","mail":"mr-zerx@yandex.ru","date":"21.11.2023, 04:51","editDate":"изменений не было"}},{"id":"tti8pb6123","content":{"name":"Иван","mail":"mr-zerx@yandex.ru","date":"21.11.2023, 05:10","editDate":"изменений не было"}},{"id":"2wm3ok5026","content":{"name":"Иван","mail":"voopoomode@gmail.combvcn","date":"21.11.2023, 05:44","editDate":"изменений не было"}},{"id":"gfes5m9742","content":{"name":"Иван","mail":"mr-zerx@yandex.ru","date":"21.11.2023, 05:45","editDate":"изменений не было"}},{"id":"5hpwey5759","content":{"name":"Иван","mail":"voopoomode@gmail.com","date":"21.11.2023, 05:45","editDate":"изменений не было"}}]}